{
	"3897":{
		"ClimateGroup":"Polar"
	},
	"3898":{
		"PoliticalProvince":"Florida",
		"Climate":"HumidSubtropical",
		"Terrain":"Lowland",
		"ClimateGroup":"Mild"
	},
	"3899":{
		"PoliticalProvince":"Georgia",
		"Climate":"HumidSubtropical",
		"Terrain":"Highland",
		"ClimateGroup":"Mild"
	},
	"3901":{
		"ClimateGroup":"Polar"
	},
	"3905":{
		"ClimateGroup":"Dry"
	},
	"3907":{
		"ClimateGroup":"Dry"
	},
	"4078":{
		"PoliticalProvince":"Florida",
		"Climate":"TropicalWet",
		"Terrain":"Lowland",
		"ClimateGroup":"Tropical"
	},
	"4079":{
		"PoliticalProvince":"Georgia",
		"Climate":"HumidSubtropical",
		"Terrain":"Lowland",
		"ClimateGroup":"Mild"
	}
}